codify4pp/__init__.py
codify4pp/generate.py
codify4pp-0.1.2.dist-info/LICENSE.txt
codify4pp-0.1.2.dist-info/METADATA
codify4pp-0.1.2.dist-info/WHEEL
codify4pp-0.1.2.dist-info/entry_points.txt
codify4pp-0.1.2.dist-info/top_level.txt
codify4pp-0.1.2.dist-info/RECORD
