Metadata-Version: 2.2
Name: codify4pp
Version: 0.1.2
Summary: A tool to create project structures for deep learning paper publication.
Author: Remosy
Author-email: remosyxu@gmail.com
Classifier: Programming Language :: Python :: 3
Classifier: License :: OSI Approved :: MIT License
Classifier: Operating System :: OS Independent
Requires-Python: >=3.7
License-File: LICENSE.txt
Dynamic: author
Dynamic: author-email
Dynamic: classifier
Dynamic: requires-python
Dynamic: summary
